odoo/addons/fetchmail_thread_default/README.rst
odoo/addons/fetchmail_thread_default/__init__.py
odoo/addons/fetchmail_thread_default/__manifest__.py
odoo/addons/fetchmail_thread_default/demo/data.xml
odoo/addons/fetchmail_thread_default/i18n/.empty
odoo/addons/fetchmail_thread_default/i18n/ca.po
odoo/addons/fetchmail_thread_default/i18n/de.po
odoo/addons/fetchmail_thread_default/i18n/es.po
odoo/addons/fetchmail_thread_default/i18n/fetchmail_thread_default.pot
odoo/addons/fetchmail_thread_default/i18n/fr.po
odoo/addons/fetchmail_thread_default/i18n/hr.po
odoo/addons/fetchmail_thread_default/i18n/it.po
odoo/addons/fetchmail_thread_default/i18n/pt_BR.po
odoo/addons/fetchmail_thread_default/i18n/pt_PT.po
odoo/addons/fetchmail_thread_default/i18n/sl.po
odoo/addons/fetchmail_thread_default/i18n/tr.po
odoo/addons/fetchmail_thread_default/i18n/zh_CN.po
odoo/addons/fetchmail_thread_default/models/__init__.py
odoo/addons/fetchmail_thread_default/models/fetchmail_server.py
odoo/addons/fetchmail_thread_default/models/mail_thread.py
odoo/addons/fetchmail_thread_default/readme/CONFIGURE.rst
odoo/addons/fetchmail_thread_default/readme/CONTRIBUTORS.rst
odoo/addons/fetchmail_thread_default/readme/DESCRIPTION.rst
odoo/addons/fetchmail_thread_default/readme/USAGE.rst
odoo/addons/fetchmail_thread_default/static/description/icon.png
odoo/addons/fetchmail_thread_default/static/description/index.html
odoo/addons/fetchmail_thread_default/tests/__init__.py
odoo/addons/fetchmail_thread_default/tests/test_fetchmail.py
odoo/addons/fetchmail_thread_default/views/fetchmail_server_view.xml
odoo_addon_fetchmail_thread_default-16.0.1.1.0.1.dist-info/METADATA
odoo_addon_fetchmail_thread_default-16.0.1.1.0.1.dist-info/WHEEL
odoo_addon_fetchmail_thread_default-16.0.1.1.0.1.dist-info/top_level.txt
odoo_addon_fetchmail_thread_default-16.0.1.1.0.1.dist-info/RECORD
